[{
  "_id": {
    "$oid": "6496f985f15bc10f660c1958"
  },
  "name": "Adversaire",
  "__v": 0,
  "pokemons": [],
  "pcStorage": "64d295c8487e7adbae453413",
  "trainingCamp": "6503272815c7b467b2da6c70"
},
{
  "_id": {
    "$oid": "649c3bdbe45d3dab76652529"
  },
  "name": "Disconnected",
  "pokemons": [],
  "__v": 0,
  "pcStorage": "64d295d38af14fe63a1c1142",
  "trainingCamp": "6503273378b1a2f57a91b41c"
},
{
  "_id": {
    "$oid": "649e0e86e45d3dab76652543"
  },
  "name": "Popole",
  "__v": 0,
  "pokemons": [],
  "pcStorage": {
    "$oid": "64d295d602f276756870fd45"
  },
  "trainingCamp": {
    "$oid": "6503273e2bb2654a36a46b6d"
  }
}]